Workbook

Sheet Dashboard
A1: SALES PERFORMANCE DASHBOARD
A2: Illustrative portfolio project | All figures use fictional sample data
A4: TOTAL REVENUE | C4: GROSS PROFIT | E4: UNITS SOLD | G4: TRANSACTIONS
A5: =SUM('Sales Data'!H2:H21) -> 129620 | C5: =SUM('Sales Data'!J2:J21) -> 65660 | E5: =SUM('Sales Data'!E2:E21) -> 208 | G5: =COUNTA('Sales Data'!A2:A21) -> 20
A9: PRODUCT PERFORMANCE | F9: REVENUE BY CHANNEL
A10: Product | B10: Units Sold | C10: Revenue (KES) | D10: Gross Profit (KES) | F10: Channel | G10: Revenue (KES)
A11: Skin Care Set | B11: =SUMIF('Sales Data'!$B$2:$B$21,A11,'Sales Data'!$E$2:$E$21) -> 23 | C11: =SUMIF('Sales Data'!$B$2:$B$21,A11,'Sales Data'!$H$2:$H$21) -> 28750 | D11: =SUMIF('Sales Data'!$B$2:$B$21,A11,'Sales Data'!$J$2:$J$21) -> 13800 | F11: Instagram | G11: =SUMIF('Sales Data'!$D$2:$D$21,F11,'Sales Data'!$H$2:$H$21) -> 43490
A12: Body Lotion | B12: =SUMIF('Sales Data'!$B$2:$B$21,A12,'Sales Data'!$E$2:$E$21) -> 51 | C12: =SUMIF('Sales Data'!$B$2:$B$21,A12,'Sales Data'!$H$2:$H$21) -> 33150 | D12: =SUMIF('Sales Data'!$B$2:$B$21,A12,'Sales Data'!$J$2:$J$21) -> 16830 | F12: WhatsApp | G12: =SUMIF('Sales Data'!$D$2:$D$21,F12,'Sales Data'!$H$2:$H$21) -> 37180
A13: Face Wash | B13: =SUMIF('Sales Data'!$B$2:$B$21,A13,'Sales Data'!$E$2:$E$21) -> 34 | C13: =SUMIF('Sales Data'!$B$2:$B$21,A13,'Sales Data'!$H$2:$H$21) -> 16320 | D13: =SUMIF('Sales Data'!$B$2:$B$21,A13,'Sales Data'!$J$2:$J$21) -> 8840 | F13: TikTok | G13: =SUMIF('Sales Data'!$D$2:$D$21,F13,'Sales Data'!$H$2:$H$21) -> 35300
A14: Sunscreen | B14: =SUMIF('Sales Data'!$B$2:$B$21,A14,'Sales Data'!$E$2:$E$21) -> 21 | C14: =SUMIF('Sales Data'!$B$2:$B$21,A14,'Sales Data'!$H$2:$H$21) -> 19950 | D14: =SUMIF('Sales Data'!$B$2:$B$21,A14,'Sales Data'!$J$2:$J$21) -> 8610 | F14: Walk-in | G14: =SUMIF('Sales Data'!$D$2:$D$21,F14,'Sales Data'!$H$2:$H$21) -> 13650
A15: Lip Balm | B15: =SUMIF('Sales Data'!$B$2:$B$21,A15,'Sales Data'!$E$2:$E$21) -> 53 | C15: =SUMIF('Sales Data'!$B$2:$B$21,A15,'Sales Data'!$H$2:$H$21) -> 13250 | D15: =SUMIF('Sales Data'!$B$2:$B$21,A15,'Sales Data'!$J$2:$J$21) -> 8480
A16: Hair Oil | B16: =SUMIF('Sales Data'!$B$2:$B$21,A16,'Sales Data'!$E$2:$E$21) -> 26 | C16: =SUMIF('Sales Data'!$B$2:$B$21,A16,'Sales Data'!$H$2:$H$21) -> 18200 | D16: =SUMIF('Sales Data'!$B$2:$B$21,A16,'Sales Data'!$J$2:$J$21) -> 9100

Sheet Sales Data
A1: Date | B1: Product | C1: Region | D1: Sales Channel | E1: Units Sold | F1: Unit Price (KES) | G1: Unit Cost (KES) | H1: Revenue (KES) | I1: Cost of Goods (KES) | J1: Gross Profit (KES)
A2: 2026-09-02 | B2: Skin Care Set | C2: Nairobi | D2: Instagram | E2: 8 | F2: 1250 | G2: 650 | H2: =E2*F2 -> 10000 | I2: =E2*G2 -> 5200 | J2: =H2-I2 -> 4800
A3: 2026-09-03 | B3: Body Lotion | C3: Kiambu | D3: WhatsApp | E3: 12 | F3: 650 | G3: 320 | H3: =E3*F3 -> 7800 | I3: =E3*G3 -> 3840 | J3: =H3-I3 -> 3960
A4: 2026-09-04 | B4: Face Wash | C4: Nairobi | D4: TikTok | E4: 10 | F4: 480 | G4: 220 | H4: =E4*F4 -> 4800 | I4: =E4*G4 -> 2200 | J4: =H4-I4 -> 2600
A5: 2026-09-05 | B5: Sunscreen | C5: Mombasa | D5: Instagram | E5: 7 | F5: 950 | G5: 540 | H5: =E5*F5 -> 6650 | I5: =E5*G5 -> 3780 | J5: =H5-I5 -> 2870
A6: 2026-09-06 | B6: Lip Balm | C6: Nakuru | D6: Walk-in | E6: 15 | F6: 250 | G6: 90 | H6: =E6*F6 -> 3750 | I6: =E6*G6 -> 1350 | J6: =H6-I6 -> 2400
A7: 2026-09-07 | B7: Hair Oil | C7: Nairobi | D7: WhatsApp | E7: 9 | F7: 700 | G7: 350 | H7: =E7*F7 -> 6300 | I7: =E7*G7 -> 3150 | J7: =H7-I7 -> 3150
A8: 2026-09-08 | B8: Skin Care Set | C8: Kiambu | D8: TikTok | E8: 6 | F8: 1250 | G8: 650 | H8: =E8*F8 -> 7500 | I8: =E8*G8 -> 3900 | J8: =H8-I8 -> 3600
A9: 2026-09-09 | B9: Body Lotion | C9: Mombasa | D9: Instagram | E9: 14 | F9: 650 | G9: 320 | H9: =E9*F9 -> 9100 | I9: =E9*G9 -> 4480 | J9: =H9-I9 -> 4620
A10: 2026-09-10 | B10: Face Wash | C10: Nakuru | D10: WhatsApp | E10: 11 | F10: 480 | G10: 220 | H10: =E10*F10 -> 5280 | I10: =E10*G10 -> 2420 | J10: =H10-I10 -> 2860
A11: 2026-09-11 | B11: Sunscreen | C11: Nairobi | D11: TikTok | E11: 8 | F11: 950 | G11: 540 | H11: =E11*F11 -> 7600 | I11: =E11*G11 -> 4320 | J11: =H11-I11 -> 3280
A12: 2026-09-12 | B12: Lip Balm | C12: Kiambu | D12: Instagram | E12: 18 | F12: 250 | G12: 90 | H12: =E12*F12 -> 4500 | I12: =E12*G12 -> 1620 | J12: =H12-I12 -> 2880
A13: 2026-09-13 | B13: Hair Oil | C13: Mombasa | D13: Walk-in | E13: 7 | F13: 700 | G13: 350 | H13: =E13*F13 -> 4900 | I13: =E13*G13 -> 2450 | J13: =H13-I13 -> 2450
... A21: 2026-09-21 | B21: Body Lotion | C21: Nakuru | D21: WhatsApp | E21: 9 | F21: 650 | G21: 320 | H21: =E21*F21 -> 5850 | I21: =E21*G21 -> 2880 | J21: =H21-I21 -> 2970
